Workbook

Sheet Roles x Areas
A1: Role access by area (version 3)
A2: V = view C = create E = edit A = approve. Combine letters (e.g. VCE). Blank = no access. Blue text = inputs you can change; add new roles in the spare rows.
A3: In ERPNext, 'A' is a workflow approval step (not a permission) and the approver must be a different person from the creator. Naira limits are on the 'Approval limits' tab.
A4: Role | B4: Web and app | C4: Stores (POS) | D4: CRM | E4: Digital media | F4: Marketing | G4: Customer success | H4: Procurement | I4: Warehouse | J4: Stock control | K4: Returns | L4: Delivery | M4: Repairs | N4: Cash-up | O4: Credit sales | P4: Expenses | Q4: Accounting | R4: Payments | S4: Payroll | T4: Tax and VAT | U4: HR and staff | V4: Assets | W4: Audit | X4: Reporting | Y4: Admin and IT | Z4: Areas accessible | AA4: Areas with approval
A5: Admin / IT | B5: VE | X5: V | Y5: VCE | Z5: =IF($A5="","",COUNTIF(B5:Y5,"?*")) -> 3 | AA5: =IF($A5="","",COUNTIF(B5:Y5,"*A*")) -> 0
A6: MD / Executive | B6: V | C6: V | D6: V | E6: VA | F6: VA | G6: V | H6: VA | I6: V | J6: VA | K6: VA | L6: V | M6: V | N6: V | O6: VA | P6: VA | Q6: V | R6: VA | S6: VA | T6: V | U6: V | V6: VA | W6: V | X6: V | Y6: VA | Z6: =IF($A6="","",COUNTIF(B6:Y6,"?*")) -> 24 | AA6: =IF($A6="","",COUNTIF(B6:Y6,"*A*")) -> 11
A7: Branch manager | B7: V | C7: VCEA | D7: VC | G7: V | I7: VCE | J7: VCEA | K7: VCEA | L7: VCE | M7: V | N7: VCE | O7: VCEA | P7: VCEA | U7: VA | V7: VC | X7: V | Z7: =IF($A7="","",COUNTIF(B7:Y7,"?*")) -> 15 | AA7: =IF($A7="","",COUNTIF(B7:Y7,"*A*")) -> 6
A8: Cashier | B8: V | C8: VC | D8: V | K8: VC | N8: VC | O8: VC | R8: V | Z8: =IF($A8="","",COUNTIF(B8:Y8,"?*")) -> 7 | AA8: =IF($A8="","",COUNTIF(B8:Y8,"*A*")) -> 0
A9: Sales rep | B9: V | C9: VC | D9: VC | I9: V | O9: VC | P9: VC | Z9: =IF($A9="","",COUNTIF(B9:Y9,"?*")) -> 6 | AA9: =IF($A9="","",COUNTIF(B9:Y9,"*A*")) -> 0
A10: Digital media | B10: VE | D10: V | E10: VCE | F10: V | X10: V | Z10: =IF($A10="","",COUNTIF(B10:Y10,"?*")) -> 5 | AA10: =IF($A10="","",COUNTIF(B10:Y10,"*A*")) -> 0
A11: Marketing manager | B11: V | D11: VE | E11: VCE | F11: VCE | G11: V | P11: VC | X11: V | Z11: =IF($A11="","",COUNTIF(B11:Y11,"?*")) -> 7 | AA11: =IF($A11="","",COUNTIF(B11:Y11,"*A*")) -> 0
A12: Customer success manager | B12: V | D12: VCE | G12: VCEA | K12: VC | L12: V | M12: V | O12: V | P12: VC | R12: V | X12: V | Z12: =IF($A12="","",COUNTIF(B12:Y12,"?*")) -> 10 | AA12: =IF($A12="","",COUNTIF(B12:Y12,"*A*")) -> 1
A13: Customer support | B13: V | D13: VCE | G13: VC | K13: VC | L13: V | M13: V | Z13: =IF($A13="","",COUNTIF(B13:Y13,"?*")) -> 6 | AA13: =IF($A13="","",COUNTIF(B13:Y13,"*A*")) -> 0
A14: Technician | D14: V | I14: VC | M14: VCE | P14: VC | Z14: =IF($A14="","",COUNTIF(B14:Y14,"?*")) -> 4 | AA14: =IF($A14="","",COUNTIF(B14:Y14,"*A*")) -> 0
A15: Warehouse officer | H15: V | I15: VCE | J15: VC | K15: VC | L15: VC | P15: VC | X15: V | Z15: =IF($A15="","",COUNTIF(B15:Y15,"?*")) -> 7 | AA15: =IF($A15="","",COUNTIF(B15:Y15,"*A*")) -> 0
A16: Stock controller | I16: V | J16: VCE | K16: V | X16: V | Z16: =IF($A16="","",COUNTIF(B16:Y16,"?*")) -> 4 | AA16: =IF($A16="","",COUNTIF(B16:Y16,"*A*")) -> 0
A17: Delivery coordinator | B17: V | D17: V | I17: V | K17: V | L17: VCE | P17: VC | Z17: =IF($A17="","",COUNTIF(B17:Y17,"?*")) -> 6 | AA17: =IF($A17="","",COUNTIF(B17:Y17,"*A*")) -> 0
A18: Rider / courier | L18: VE | N18: VC | P18: VC | Z18: =IF($A18="","",COUNTIF(B18:Y18,"?*")) -> 3 | AA18: =IF($A18="","",COUNTIF(B18:Y18,"*A*")) -> 0
A19: Procurement officer | H19: VCE | I19: V | Q19: V | V19: VCE | X19: V | Z19: =IF($A19="","",COUNTIF(B19:Y19,"?*")) -> 5 | AA19: =IF($A19="","",COUNTIF(B19:Y19,"*A*")) -> 0
A20: Credit controller | D20: V | O20: VCE | Q20: V | R20: V | X20: V | Z20: =IF($A20="","",COUNTIF(B20:Y20,"?*")) -> 5 | AA20: =IF($A20="","",COUNTIF(B20:Y20,"*A*")) -> 0
A21: Cash controller | N21: VCEA | P21: VCE | Q21: V | R21: V | X21: V | Z21: =IF($A21="","",COUNTIF(B21:Y21,"?*")) -> 5 | AA21: =IF($A21="","",COUNTIF(B21:Y21,"*A*")) -> 1
A22: Accountant | C22: V | H22: V | N22: V | O22: VCE | P22: VCE | Q22: VCE | R22: VCE | S22: V | T22: VCE | V22: VCE | X22: V | Z22: =IF($A22="","",COUNTIF(B22:Y22,"?*")) -> 11 | AA22: =IF($A22="","",COUNTIF(B22:Y22,"*A*")) -> 0
A23: HR officer | S23: VCE | U23: VCE | X23: V | Z23: =IF($A23="","",COUNTIF(B23:Y23,"?*")) -> 3 | AA23: =IF($A23="","",COUNTIF(B23:Y23,"*A*")) -> 0
A24: Auditor | B24: V | C24: V | D24: V | E24: V | F24: V | G24: V | H24: V | I24: V | J24: VC | K24: V | L24: V | M24: V | N24: V | O24: V | P24: V | Q24: V | R24: V | S24: V | T24: V | U24: V | V24: VC | W24: VC | X24: V | Z24: =IF($A24="","",COUNTIF(B24:Y24,"?*")) -> 23 | AA24: =IF($A24="","",COUNTIF(B24:Y24,"*A*")) -> 0
Z25: =IF($A25="","",COUNTIF(B25:Y25,"?*")) | AA25: =IF($A25="","",COUNTIF(B25:Y25,"*A*"))
Z26: =IF($A26="","",COUNTIF(B26:Y26,"?*")) | AA26: =IF($A26="","",COUNTIF(B26:Y26,"*A*"))
Z27: =IF($A27="","",COUNTIF(B27:Y27,"?*")) | AA27: =IF($A27="","",COUNTIF(B27:Y27,"*A*"))
Z28: =IF($A28="","",COUNTIF(B28:Y28,"?*")) | AA28: =IF($A28="","",COUNTIF(B28:Y28,"*A*"))
Z29: =IF($A29="","",COUNTIF(B29:Y29,"?*")) | AA29: =IF($A29="","",COUNTIF(B29:Y29,"*A*"))
Z30: =IF($A30="","",COUNTIF(B30:Y30,"?*")) | AA30: =IF($A30="","",COUNTIF(B30:Y30,"*A*"))
Z31: =IF($A31="","",COUNTIF(B31:Y31,"?*")) | AA31: =IF($A31="","",COUNTIF(B31:Y31,"*A*"))
Z32: =IF($A32="","",COUNTIF(B32:Y32,"?*")) | AA32: =IF($A32="","",COUNTIF(B32:Y32,"*A*"))
Z33: =IF($A33="","",COUNTIF(B33:Y33,"?*")) | AA33: =IF($A33="","",COUNTIF(B33:Y33,"*A*"))
Z34: =IF($A34="","",COUNTIF(B34:Y34,"?*")) | AA34: =IF($A34="","",COUNTIF(B34:Y34,"*A*"))
A36: Shading: green = can approve, blue = can create or edit, grey = view only.
A37: Changes from v1: added Marketing, Customer success, Stock control, Returns, Cash-up, Credit sales, Expenses and Assets areas; added 6 roles; removed self-approval (Accountant, Admin / IT, Delivery coordinator); price changes now approved by MD.

Sheet Approval limits
A1: Approval limits (suggested, confirm with the MD)
A2: Starting values from the MD-perspective review. Rows marked PLACEHOLDER are my own guesses with no review; set the real values. Blue cells are inputs; change them to the company's real limits. Amounts in Naira (NGN).
A4: Control | B4: Who acts | C4: Limit | D4: Unit | E4: Above the limit
A5: Discount at till | B5: Cashier | C5: 0 | D5: % of sale | E5: Branch manager
A6: Discount | B6: Branch manager | C6: 3 | D6: % of sale | E6: MD
A7: Refund or void | B7: Branch manager | C7: 50000 | D7: NGN per item | E7: MD
A8: Stock write-off | B8: Branch manager, with Auditor | C8: 100000 | D8: NGN per write-off | E8: MD
A9: Purchase order | B9: Procurement officer | C9: 500000 | D9: NGN per PO | E9: MD
A10: New supplier | B10: Procurement officer | C10: 2 | D10: approvals needed | E10: (also TIN check)
A11: Payout, single payee | B11: Accountant prepares | C11: 100000 | D11: NGN per payee | E11: MD one-time code
A12: Payout, batch | B12: Accountant prepares | C12: 1000000 | D12: NGN per batch | E12: MD one-time code
A13: Payout, daily cap | B13: System | C13: 2000000 | D13: NGN per day | E13: Blocked
A14: Payee account change hold | B14: System | C14: 24 | D14: hours | E14: Released after hold
A15: Price change | B15: Digital media / Marketing | C15: 5 | D15: % margin shift | E15: MD
A16: PLACEHOLDER: credit limit change | B16: Credit controller | C16: 500000 | D16: NGN per customer | E16: MD
... A21: PLACEHOLDER: asset disposal or write-off | B21: Accountant prepares | C21: 0 | D21: NGN (always MD) | E21: MD

Sheet Data scope
A1: Data limits (which records a role may see)
A2: Area access gives screens; these rules limit records inside them. In ERPNext: User Permissions on Company/Branch/Warehouse/Cost Center; 'own records' uses owner-based rules or a query hook.
A4: Role | B4: Limited to | C4: Notes
A5: Branch manager | B5: Own branch | C5: Stock, sales, cash-up and staff of that branch only
A6: Cashier | B6: Own branch, own shift | C6: No price edits, no cost price, no discounts
A7: Sales rep | B7: Own branch, own orders | C7: Orders they created
A8: Technician | B8: Own repair centre | C8: Jobs assigned; parts from the spares store only
A9: Warehouse officer | B9: Warehouse | C9: Cannot approve own stock adjustments
A10: Stock controller | B10: Assigned branches | C10: Independent counts; reports to MD or Auditor, not branch
A11: Delivery coordinator | B11: All deliveries | C11: No payment details
A12: Rider / courier | B12: Own trips | C12: Proof of delivery and cash remittance only
A13: Customer success manager | B13: All customers | C13: No cost prices or payroll
A14: Marketing manager | B14: Customers (no payment data) | C14: Promotion and campaign data only
A15: Cash controller | B15: All branches | C15: Cash-up, deposits and petty cash floats; cannot post sales
... A21: Admin / IT | B21: System setup | C21: No access to payroll or HR; cannot grant own access; MD holds a break-glass admin account

Sheet Screens
A1: Screen registry (drives what each person sees)
A2: Generate this list from ERPNext roles, not a second copy: a screen shows only when the user's role has at least View on its area. Add a row to add a screen.
A4: Screen | B4: Area | C4: Main ERPNext records | D4: Roles with access | E4: Custom code?
A5: Online orders | B5: Web and app | C5: Sales Order, Website Item, Shopping Cart | D5: =COUNTIF(INDEX('Roles x Areas'!$B$5:$Y$34,0,MATCH(B5,'Roles x Areas'!$B$4:$Y$4,0)),"?*") -> 11 | E5: Yes (customer app)
A6: Till | B6: Stores (POS) | C6: POS Invoice, POS Profile, Opening and Closing Entry | D6: =COUNTIF(INDEX('Roles x Areas'!$B$5:$Y$34,0,MATCH(B6,'Roles x Areas'!$B$4:$Y$4,0)),"?*") -> 6 | E6: Yes (scan-and-pay UI)
A7: Customer accounts | B7: CRM | C7: Customer, Lead, Contact | D7: =COUNTIF(INDEX('Roles x Areas'!$B$5:$Y$34,0,MATCH(B7,'Roles x Areas'!$B$4:$Y$4,0)),"?*") -> 12 | E7: No
A8: Content and prices | B8: Digital media | C8: Item, Price List, Pricing Rule | D8: =COUNTIF(INDEX('Roles x Areas'!$B$5:$Y$34,0,MATCH(B8,'Roles x Areas'!$B$4:$Y$4,0)),"?*") -> 4 | E8: No
A9: Campaigns and promotions | B9: Marketing | C9: Campaign, Coupon Code, Pricing Rule | D9: =COUNTIF(INDEX('Roles x Areas'!$B$5:$Y$34,0,MATCH(B9,'Roles x Areas'!$B$4:$Y$4,0)),"?*") -> 4 | E9: Light
A10: Customer care | B10: Customer success | C10: Issue, Customer feedback (custom) | D10: =COUNTIF(INDEX('Roles x Areas'!$B$5:$Y$34,0,MATCH(B10,'Roles x Areas'!$B$4:$Y$4,0)),"?*") -> 6 | E10: Light
A11: Purchase orders | B11: Procurement | C11: Supplier, Material Request, Purchase Order, Purchase Receipt | D11: =COUNTIF(INDEX('Roles x Areas'!$B$5:$Y$34,0,MATCH(B11,'Roles x Areas'!$B$4:$Y$4,0)),"?*") -> 5 | E11: No
A12: Stock and transfers | B12: Warehouse | C12: Bin, Stock Entry, Putaway | D12: =COUNTIF(INDEX('Roles x Areas'!$B$5:$Y$34,0,MATCH(B12,'Roles x Areas'!$B$4:$Y$4,0)),"?*") -> 9 | E12: No
A13: Counts and write-offs | B13: Stock control | C13: Stock Reconciliation, Write-off workflow | D13: =COUNTIF(INDEX('Roles x Areas'!$B$5:$Y$34,0,MATCH(B13,'Roles x Areas'!$B$4:$Y$4,0)),"?*") -> 5 | E13: Light (workflow)
A14: Returns | B14: Returns | C14: Sales Return, Purchase Return, Quarantine warehouse | D14: =COUNTIF(INDEX('Roles x Areas'!$B$5:$Y$34,0,MATCH(B14,'Roles x Areas'!$B$4:$Y$4,0)),"?*") -> 9 | E14: Light
A15: Dispatch board | B15: Delivery | C15: Delivery Note, Delivery Trip, Proof of delivery (custom) | D15: =COUNTIF(INDEX('Roles x Areas'!$B$5:$Y$34,0,MATCH(B15,'Roles x Areas'!$B$4:$Y$4,0)),"?*") -> 8 | E15: Yes (rider app)
A16: Repair jobs | B16: Repairs | C16: Repair Job (custom), Stock Entry for parts | D16: =COUNTIF(INDEX('Roles x Areas'!$B$5:$Y$34,0,MATCH(B16,'Roles x Areas'!$B$4:$Y$4,0)),"?*") -> 6 | E16: Yes
... A30: Users and roles | B30: Admin and IT | C30: User, Role, User Permission | D30: =COUNTIF(INDEX('Roles x Areas'!$B$5:$Y$34,0,MATCH(B30,'Roles x Areas'!$B$4:$Y$4,0)),"?*") -> 2 | E30: No
