Workbook

Sheet Screens
A1: Screen inventory: what ERPNext offers versus what to build
A2: Verdict: Use ERPNext = admins and finance use the standard Desk; Configure ERPNext = ERPNext handles it, our screen is thin; Build custom = no adequate ERPNext screen. Edit the blue cells to re-plan.
A4: ID | B4: Area | C4: Screen | D4: Main roles | E4: What ERPNext offers | F4: Verdict | G4: Pattern | H4: Device | I4: Offline | J4: Scope | K4: Sprint
A5: P01 | B5: Platform | C5: Login and device registration | D5: All | E5: User, session | F5: Build custom | G5: Form | H5: All | I5: Partial | J5: MVP | K5: S1
A6: P02 | B6: Platform | C6: Role home (task queue) | D6: All | E6: Workspace (too cluttered) | F6: Build custom | G6: Dashboard | H6: All | I6: Cached | J6: MVP | K6: S1
A7: P03 | B7: Platform | C7: Offline and sync tray | D7: All | E7: None | F7: Build custom | G7: List | H7: All | I7: Yes | J7: MVP | K7: S2
A8: P04 | B8: Platform | C8: Notifications | D8: All | E8: Notification | F8: Configure ERPNext | G8: List | H8: All | I8: No | J8: Later | K8: S6
A9: P05 | B9: Platform | C9: Config console (screens, roles, branding) | D9: Admin / IT | E9: None | F9: Build custom | G9: Form | H9: Desktop | I9: No | J9: Later | K9: S10
A10: S01 | B10: Stores (POS) | C10: Till (scan and pay) | D10: Cashier | E10: POS Invoice, POS Profile | F10: Build custom | G10: Scan flow | H10: Tablet | I10: Yes | J10: MVP | K10: S2
A11: S02 | B11: Stores (POS) | C11: Parked sales | D11: Cashier | E11: Draft invoice | F11: Build custom | G11: List | H11: Tablet | I11: Yes | J11: MVP | K11: S2
A12: S03 | B12: Stores (POS) | C12: Shift open and close | D12: Cashier | E12: POS Opening and Closing Entry | F12: Configure ERPNext | G12: Wizard | H12: Tablet | I12: Yes | J12: MVP | K12: S2
A13: S04 | B13: Stores (POS) | C13: Customer lookup | D13: Cashier, Sales rep | E13: Customer | F13: Configure ERPNext | G13: List | H13: Tablet, phone | I13: Cached | J13: MVP | K13: S2
A14: S05 | B14: Stores (POS) | C14: Needs-manager request (discount, void) | D14: Cashier | E14: None | F14: Build custom | G14: Dialog | H14: Tablet | I14: No | J14: MVP | K14: S3
A15: S06 | B15: Stores (POS) | C15: Stock check and order | D15: Sales rep | E15: Item, Bin, Sales Order | F15: Build custom | G15: Scan flow | H15: Phone | I15: Cached | J15: Later | K15: S8
... A97: AS06 | B97: Assets | C97: Asset count and verification by scanning tag | D97: Auditor, Stock controller | E97: None | F97: Build custom | G97: Scan flow | H97: Tablet | I97: Yes | J97: Later | K97: After S10

Sheet Sprints
A1: Front-end sprint plan (two-week sprints)
A2: Assumes about 20 productive hours a week for one part-time developer plus Claude Code. Blue cells are inputs. Plan written 31 Oct 2026.
A4: Sprint | B4: Dates | C4: Goal | D4: Delivers | E4: Demo outcome | F4: Planned hours | G4: Screens in sprint
A5: S1 | B5: 2 to 13 Nov 2026 | C5: Foundation | D5: Monorepo, CI, mock server, tenant.json loader, design tokens, app shell, login, permission-driven navigation for 3 roles, offline bar | E5: Log in as 3 roles and see different menus; swap tokens; rebrand from tenant.json | F5: 40 | G5: =COUNTIF(Screens!$K$5:$K$97,A5) -> 2
A6: S2 | B6: 16 to 27 Nov 2026 | C6: Cashier core | D6: Offline queue with idempotency keys, scanner, Till, parked sales, shift open and close, sync tray, A5 invoice and receipt printing through the browser | E6: Ring a sale offline on a tablet, reconnect, see it post once | F6: 40 | G6: =COUNTIF(Screens!$K$5:$K$97,A6) -> 6
A7: S3 | B7: 30 Nov to 11 Dec 2026 | C7: Cash and approvals | D7: Returns, needs-manager request, credit sale at till, approvals inbox, cash-up count and sign-off, manager home, cash-up variance report, stock request | E7: Cashier asks for a discount, manager approves on phone, cash-up shows variance | F7: 40 | G7: =COUNTIF(Screens!$K$5:$K$97,A7) -> 9
A8: S4 | B8: 14 to 25 Dec 2026 | C8: Stock and delivery slice | D8: Goods and transfer receipt, blind count, write-off request, dispatch board, rider trips, proof of delivery, cash remittance, in-transit report | E8: Receive a transfer by scan; rider completes a delivery offline with photo | F8: 40 | G8: =COUNTIF(Screens!$K$5:$K$97,A8) -> 12
A9: Buffer | B9: 28 to 31 Dec 2026 | C9: Handover | D9: Bug fixes, runbook, Storybook, test report, handover session | E9: Second person runs it from the runbook | F9: 10 | G9: =COUNTIF(Screens!$K$5:$K$97,A9) -> 0
A10: S5 | B10: Jan 2027 | C10: ERPNext adapter (reads) | D10: Read adapter against staging ERPNext, contract tests on both adapters | E10: Same screens show real data | F10: 40 | G10: =COUNTIF(Screens!$K$5:$K$97,A10) -> 0
A11: S6 | B11: Jan to Feb 2027 | C11: Adapter writes and pilot hardening | D11: Write adapter, 3G testing, fixes from cashier and rider feedback, notifications, attendance view, customer payments and statements, expense requests and approval | E11: Pilot cashier sells on real back end | F11: 40 | G11: =COUNTIF(Screens!$K$5:$K$97,A11) -> 6
A12: S7 | B12: Feb 2027 | C12: Loss reports and stock extras | D12: Unbanked cash, refunds and voids, count variance, negative stock, failed deliveries, quarantine, returns inspection, serial check, cross-branch cash-up, receivables ageing, credit limits, petty cash | E12: Daily loss report runs for pilot branch | F12: 40 | G12: =COUNTIF(Screens!$K$5:$K$97,A12) -> 12
A13: S8 | B13: Mar 2027 | C13: Repairs and sales rep | D13: Repair intake, jobs, parts, quote; rep stock check and order | E13: Technician logs a repair end to end | F13: 40 | G13: =COUNTIF(Screens!$K$5:$K$97,A13) -> 5
A14: S9 | B14: Mar 2027 | C14: Payments and payouts | D14: Paystack reconciliation, payee whitelist, payout batch, VAT, online orders queue, Paystack report | E14: Payout batch needs MD code | F14: 40 | G14: =COUNTIF(Screens!$K$5:$K$97,A14) -> 6
A15: S10 | B15: Apr 2027 | C15: MD view and config | D15: MD dashboard, price and margin report, break-glass access, config console, design system swap | E15: Second company rebranded from config only | F15: 40 | G15: =COUNTIF(Screens!$K$5:$K$97,A15) -> 4
C16: Total planned hours | F16: =SUM(F5:F15) -> 410
C17: Hours before 31 Dec (S1 to Buffer) | F17: =SUM(F5:F9) -> 170
C18: Note: about 8.5 weeks (roughly 170 hours) remain before 31 Dec 2026, so only S1 to S4 plus a handover buffer fit. S5 onward needs a continuing owner.

Sheet Summary
A1: Summary (updates when the Screens tab changes)
A3: Verdict | B3: Screens | C3: Of which MVP
A4: Use ERPNext | B4: =COUNTIF(Screens!$F$5:$F$97,A4) -> 8 | C4: =COUNTIFS(Screens!$F$5:$F$97,A4,Screens!$J$5:$J$97,"MVP") -> 0
A5: Configure ERPNext | B5: =COUNTIF(Screens!$F$5:$F$97,A5) -> 35 | C5: =COUNTIFS(Screens!$F$5:$F$97,A5,Screens!$J$5:$J$97,"MVP") -> 6
A6: Build custom | B6: =COUNTIF(Screens!$F$5:$F$97,A6) -> 50 | C6: =COUNTIFS(Screens!$F$5:$F$97,A6,Screens!$J$5:$J$97,"MVP") -> 23
A7: Total | B7: =SUM(B4:B6) -> 93 | C7: =SUM(C4:C6) -> 29
A9: Note: the product manager's MVP list included unbanked cash; it is placed in S7 here because it needs deposit data from the back end.
